IsoConverter/__init__.py
IsoConverter/go.py
IsoConverter-0.0.1.dist-info/License.txt
IsoConverter-0.0.1.dist-info/METADATA
IsoConverter-0.0.1.dist-info/WHEEL
IsoConverter-0.0.1.dist-info/top_level.txt
IsoConverter-0.0.1.dist-info/RECORD
